thejoker/__init__.py
thejoker/_astropy_init.py
thejoker/_compiler.c
thejoker/compiler_version.cpython-39-darwin.so
thejoker/conftest.py
thejoker/data.py
thejoker/data_helpers.py
thejoker/distributions.py
thejoker/exceptions.py
thejoker/likelihood_helpers.py
thejoker/logging.py
thejoker/multiproc_helpers.py
thejoker/plot.py
thejoker/prior.py
thejoker/prior_helpers.py
thejoker/samples.py
thejoker/samples_analysis.py
thejoker/samples_helpers.py
thejoker/thejoker.py
thejoker/utils.py
thejoker/version.py
thejoker/src/__init__.py
thejoker/src/fast_likelihood.c
thejoker/src/fast_likelihood.cpython-39-darwin.so
thejoker/src/fast_likelihood.pyx
thejoker/src/setup_package.py
thejoker/src/tests/__init__.py
thejoker/src/tests/py_likelihood.py
thejoker/src/tests/test_fast_likelihood.py
thejoker/tests/__init__.py
thejoker/tests/setup_package.py
thejoker/tests/test_data.py
thejoker/tests/test_likelihood_helpers.py
thejoker/tests/test_plot.py
thejoker/tests/test_prior.py
thejoker/tests/test_sampler.py
thejoker/tests/test_samples.py
thejoker/tests/test_samples_analysis.py
thejoker/tests/test_utils.py
thejoker-1.2.2.dist-info/LICENSE
thejoker-1.2.2.dist-info/METADATA
thejoker-1.2.2.dist-info/WHEEL
thejoker-1.2.2.dist-info/top_level.txt
thejoker-1.2.2.dist-info/RECORD
