Metadata-Version: 2.1
Name: thejoker
Version: 1.2.2
Summary: A custom Monte Carlo sampler for the two-body problem.
Home-page: https://github.com/adrn/thejoker
Author: Adrian Price-Whelan
Author-email: adrianmpw@gmail.com
License: MIT
Platform: UNKNOWN
Requires-Python: >=3.7
Provides-Extra: test
Provides-Extra: docs
License-File: LICENSE
